pycbpf/__init__.py
pycbpf/c2ebpf.py
pycbpf/cbpf2c.py
pycbpf/filter2cbpf.py
pycbpf-0.0.2.dist-info/LICENSE
pycbpf-0.0.2.dist-info/METADATA
pycbpf-0.0.2.dist-info/WHEEL
pycbpf-0.0.2.dist-info/top_level.txt
pycbpf-0.0.2.dist-info/RECORD
