Metadata-Version: 2.1
Name: pycbpf
Version: 0.0.2
Summary: convert cbpf code to C for BCC
Author-email: junka <wan.junjie@foxmail.com>
Project-URL: Homepage, https://github.com/junka/pycbpf
Project-URL: Bug Tracker, https://github.com/junka/pycbpf/issues
Classifier: Programming Language :: Python :: 3
Classifier: License :: OSI Approved :: MIT License
Classifier: Operating System :: POSIX :: Linux
Requires-Python: >=3.7
License-File: LICENSE
Requires-Dist: libpcap
